citoplasm/__init__.py
citoplasm/cito.py
citoplasm/context.py
citoplasm/util.py
citoplasm/agent/__init__.py
citoplasm/agent/agent.py
citoplasm/agent/openai_chat_agent.py
citoplasm/functions/__init__.py
citoplasm/functions/ask.py
citoplasm/functions/chain.py
citoplasm/functions/compare.py
citoplasm/functions/verify.py
citoplasm/tools/__init__.py
citoplasm/tools/python.py
citoplasm/tools/search.py
citoplasm-0.0.5.dist-info/METADATA
citoplasm-0.0.5.dist-info/WHEEL
citoplasm-0.0.5.dist-info/licenses/LICENSE
citoplasm-0.0.5.dist-info/RECORD
